Metadata-Version: 2.1
Name: sowerest
Version: 0.0.12
Summary: HTTP REST client, simplified for SeWeMail API
Home-page: https://github.com/sowemail/sowerest
Author: Fourat Zouari
Author-email: fourat@gmail.com
License: MIT
Download-URL: https://github.com/sowemail/sowerest/tarball/0.0.12
Keywords: REST,HTTP,API,SOWEMAIL
Platform: UNKNOWN
Classifier: Programming Language :: Python :: 3
Classifier: Programming Language :: Python :: 3.4
Classifier: Programming Language :: Python :: 3.5
Classifier: Programming Language :: Python :: 3.6
Classifier: Programming Language :: Python :: 3.7
Requires-Python: >=3.4.*
